clubhead_db/__init__.py
clubhead_db/builder.py
clubhead_db/data_processor.py
clubhead_db/label_merger.py
clubhead_db/data/annotations.parquet
clubhead_db/data/metadata.csv
clubhead_db-1.0.1.dist-info/METADATA
clubhead_db-1.0.1.dist-info/WHEEL
clubhead_db-1.0.1.dist-info/entry_points.txt
clubhead_db-1.0.1.dist-info/top_level.txt
clubhead_db-1.0.1.dist-info/RECORD
