Metadata-Version: 2.4
Name: clubhead-db
Version: 1.0.1
Summary: Scripts to download and prepare the ClubheadDB dataset.
Author-email: anonymousauthor23 <algorithmartist02@gmail.com>
License: CC-BY-NC-4.0
Project-URL: Homepage, https://github.com/unknownauthor23/ClubheadDB
Classifier: Programming Language :: Python :: 3
Classifier: Operating System :: OS Independent
Requires-Python: >=3.8
Requires-Dist: pandas
Requires-Dist: pyarrow
Requires-Dist: tqdm
